odoo9_addon_hr_skill-9.0.1.0.0-py2.7-nspkg.pth
odoo9_addon_hr_skill-9.0.1.0.0.dist-info/DESCRIPTION.rst
odoo9_addon_hr_skill-9.0.1.0.0.dist-info/METADATA
odoo9_addon_hr_skill-9.0.1.0.0.dist-info/RECORD
odoo9_addon_hr_skill-9.0.1.0.0.dist-info/WHEEL
odoo9_addon_hr_skill-9.0.1.0.0.dist-info/metadata.json
odoo9_addon_hr_skill-9.0.1.0.0.dist-info/namespace_packages.txt
odoo9_addon_hr_skill-9.0.1.0.0.dist-info/top_level.txt
odoo_addons/hr_skill/README.rst
odoo_addons/hr_skill/__init__.py
odoo_addons/hr_skill/__openerp__.py
odoo_addons/hr_skill/i18n/ar.po
odoo_addons/hr_skill/i18n/de.po
odoo_addons/hr_skill/i18n/es.po
odoo_addons/hr_skill/i18n/fi.po
odoo_addons/hr_skill/i18n/fr.po
odoo_addons/hr_skill/i18n/hr_skill.pot
odoo_addons/hr_skill/i18n/it.po
odoo_addons/hr_skill/i18n/pl.po
odoo_addons/hr_skill/i18n/pt_BR.po
odoo_addons/hr_skill/i18n/ro.po
odoo_addons/hr_skill/i18n/sl.po
odoo_addons/hr_skill/i18n/sv.po
odoo_addons/hr_skill/models/__init__.py
odoo_addons/hr_skill/models/hr_employee.py
odoo_addons/hr_skill/models/hr_skill.py
odoo_addons/hr_skill/security/ir.model.access.csv
odoo_addons/hr_skill/static/description/icon.png
odoo_addons/hr_skill/views/hr_employee.xml
odoo_addons/hr_skill/views/hr_skill.xml
